diner/__init__.py
diner/diner.py
diner-0.0.1.dist-info/METADATA
diner-0.0.1.dist-info/WHEEL
diner-0.0.1.dist-info/entry_points.txt
diner-0.0.1.dist-info/top_level.txt
diner-0.0.1.dist-info/RECORD
